{"validationEntity":{"analysedDataType":"auto","dataResult":{"createdDate":"2024-07-29T06:19:34Z"}},"id":"2D1CA7ED-5D05-4DB9-99AA-5D14CA9ADD18","createdDate":"2024-07-29T06:15:05Z","trainingEntity":{"validationResults":{"generalRegressor":{"maximumError":694.8439790218545,"rootMeanSquaredError":176.87807805762287}},"validationAccuracy":176.87807805762287,"checkpointMetrics":{},"featureExtractionCheckpointMayBeAvailable":false,"dataResult":{"dataAnalysis":{"regressorAnalysis":{"targetRange":[19216,45224]},"classifierAnalysis":{},"summary":{"sampleCount":10000,"canUseValidation":1},"issues":[{"severity":"info","description":"Data has 10000 rows"}]},"itemsCount":10000,"createdDate":"2024-07-29T06:19:34Z","columns":["wake","estimatedSleep","coffee","actualSleep"],"dataSourceID":"9E1E9E2C-F91A-4803-960D-F0310B7427E8","dataURL":"file:\/\/\/Users\/trm\/Developer\/MOTT%20APPLICATIONS\/CODE\/100-DAYS-OF-SWIFTUI\/6%20-%20WeRest\/BetterRest.csv","columnValues":["31,500.00, 32,400.00, 26,100.00, 40,500.00, 19,800.00, 27,000.00, 20,700.00, 21,600.00, 41,400.00, 34,200.00, 21,600.00, 78,300.00, 32,400.00, 28,800.00, 18,900.00, 18,000.00, 28,800.00, 18,000.00, 7,200.00, 35,100.00, 24,300.00, 35,100.00, 34,200.00, 27,900.00, 30,600.00, 69,300.00, 35,100.00, 34,200.00, 34,200.00, 23,400.00","9.00, 5.00, 6.50, 8.75, 6.00, 7.50, 9.25, 6.00, 9.25, 6.75, 5.25, 9.25, 10.00, 8.75, 8.25, 6.25, 10.00, 6.25, 10.00, 9.50, 5.00, 7.50, 6.25, 8.00, 8.00, 6.50, 8.00, 10.00, 8.25, 8.00","6.00, 2.00, 10.00, 4.00, 3.00, 1.00, 1.00, 3.00, 5.00, 8.00, 3.00, 8.00, 2.00, 3.00, 1.00, 2.00, 3.00, 2.00, 1.00, 4.00, 2.00, 1.00, 1.00, 4.00, 3.00, 7.00, 4.00, 4.00, 1.00, 3.00","38,230.00, 20,180.00, 31,989.00, 35,258.00, 24,487.00, 28,300.00, 34,548.00, 24,557.00, 37,836.00, 31,340.00, 21,874.00, 40,405.00, 38,076.00, 34,265.00, 30,936.00, 24,665.00, 39,007.00, 24,578.00, 37,267.00, 37,878.00, 20,220.00, 28,400.00, 23,882.00, 32,427.00, 31,699.00, 29,670.00, 32,789.00, 39,792.00, 30,935.00, 31,701.00"],"targetRange":[19216,45224],"columnTypes":["Double","Double","Double","Double"]},"startTime":"2024-07-29T06:27:30Z","analysedDataType":"datasource","trainingResults":{"generalRegressor":{"maximumError":700.7884351177563,"rootMeanSquaredError":177.06208892898567}},"snapshottableCheckpoints":{},"progress":[],"dataSourceID":"9E1E9E2C-F91A-4803-960D-F0310B7427E8","trainingAccuracy":177.06208892898567,"finishTime":"2024-07-29T06:27:31Z"},"modifiedDate":"2024-07-29T06:27:39Z","settingEntity":{"suggestedColumnTypes":["Double","Double","Double","Double"],"styleTransferAlgorithmType":"image","algorithmType":"maxEnt","seedType":"default","suggestedColumnValues":["31,500.00, 32,400.00, 26,100.00, 40,500.00, 19,800.00, 27,000.00, 20,700.00, 21,600.00, 41,400.00, 34,200.00, 21,600.00, 78,300.00, 32,400.00, 28,800.00, 18,900.00, 18,000.00, 28,800.00, 18,000.00, 7,200.00, 35,100.00, 24,300.00, 35,100.00, 34,200.00, 27,900.00, 30,600.00, 69,300.00, 35,100.00, 34,200.00, 34,200.00, 23,400.00","9.00, 5.00, 6.50, 8.75, 6.00, 7.50, 9.25, 6.00, 9.25, 6.75, 5.25, 9.25, 10.00, 8.75, 8.25, 6.25, 10.00, 6.25, 10.00, 9.50, 5.00, 7.50, 6.25, 8.00, 8.00, 6.50, 8.00, 10.00, 8.25, 8.00","6.00, 2.00, 10.00, 4.00, 3.00, 1.00, 1.00, 3.00, 5.00, 8.00, 3.00, 8.00, 2.00, 3.00, 1.00, 2.00, 3.00, 2.00, 1.00, 4.00, 2.00, 1.00, 1.00, 4.00, 3.00, 7.00, 4.00, 4.00, 1.00, 3.00","38,230.00, 20,180.00, 31,989.00, 35,258.00, 24,487.00, 28,300.00, 34,548.00, 24,557.00, 37,836.00, 31,340.00, 21,874.00, 40,405.00, 38,076.00, 34,265.00, 30,936.00, 24,665.00, 39,007.00, 24,578.00, 37,267.00, 37,878.00, 20,220.00, 28,400.00, 23,882.00, 32,427.00, 31,699.00, 29,670.00, 32,789.00, 39,792.00, 30,935.00, 31,701.00"],"handActionClassifierAugmentations":[],"harVideoAugmentations":0,"transferLearningEmbeddingType":"dynamic","suggestedColumns":["wake","estimatedSleep","coffee","actualSleep"],"targetColumn":"actualSleep","featureNames":["wake","estimatedSleep","coffee"],"taskType":"generalRegresor","handPoseClassifierAugmentations":[],"generalRegressorType":{"auto":{}},"augmentations":[]},"preferredFilename":"WeRest 1","version":"1.0","evaluationContainerEntity":{"previewType":"tabularRegressor","evaluationEntities":[{"createdDate":"2024-07-29T06:27:39Z","id":"e41be16e-6853-476d-8caf-9a84883399fe","dataResult":{},"analysedDataType":"none"}],"testingEvaluationEntity":{"analysedDataType":"none","id":"9ec9cddf-e9c8-466f-a409-86a338a168e1","dataResult":{"createdDate":"2024-07-29T06:19:34Z"},"createdDate":"2024-07-29T06:15:05Z"},"validationEvaluationEntity":{"id":"be5fa6da-25fa-4d3e-86f2-19069e75bbeb","dataResult":{"createdDate":"2024-07-29T06:19:34Z"},"analysedDataType":"auto","evaluationResult":{"generalRegressor":{"rootMeanSquaredError":176.87807805762287,"maximumError":694.8439790218545}},"createdDate":"2024-07-29T06:15:05Z"},"modifiedDate":"2024-07-29T06:27:39Z","id":"3a710226-2bc8-409c-98a9-2878b64ac179","trainingEvaluationEntity":{"id":"1f362304-a72a-40a2-b7f7-75010530982d","createdDate":"2024-07-29T06:15:05Z","dataSourceID":"9E1E9E2C-F91A-4803-960D-F0310B7427E8","dataResult":{"dataSourceID":"9E1E9E2C-F91A-4803-960D-F0310B7427E8","itemsCount":10000,"targetRange":[19216,45224],"dataAnalysis":{"classifierAnalysis":{},"issues":[{"severity":"info","description":"Data has 10000 rows"}],"summary":{"sampleCount":10000,"canUseValidation":1},"regressorAnalysis":{"targetRange":[19216,45224]}},"dataURL":"file:\/\/\/Users\/trm\/Developer\/MOTT%20APPLICATIONS\/CODE\/100-DAYS-OF-SWIFTUI\/6%20-%20WeRest\/BetterRest.csv","createdDate":"2024-07-29T06:19:34Z"},"evaluationResult":{"generalRegressor":{"rootMeanSquaredError":177.06208892898567,"maximumError":700.7884351177563}},"analysedDataType":"none"},"createdDate":"2024-07-29T06:27:39Z"},"title":"WeRest 1","snapshotRole":{"withoutSnapshots":0},"state":"trained","modelEntity":{"title":"","experimentID":"2D1CA7ED-5D05-4DB9-99AA-5D14CA9ADD18","version":"1.0","modelURL":"Models\/WeRest%201.mlmodel","modifiedDate":"2024-07-29T06:15:05Z","createdDate":"2024-07-29T06:15:05Z","preferredFilename":"","id":"89FCDB83-6101-49CE-B65D-118D1D26BAC1"},"evaluationState":"uninitialized","contentDataResult":{"createdDate":"2024-07-29T06:19:34Z"},"evaluationEntity":{"id":"f15cf626-8069-434f-9b2d-30c65b0bf43e","dataResult":{},"analysedDataType":"none"},"activityEntities":["trainingDataAdded",[{"subtitle":"BetterRest.csv","id":"94DE5BC6-F4CC-4EB0-A2D0-2B047ED6C982","event":"trainingDataAdded","title":"Training Data Added","createdDate":"2024-07-29T06:19:37Z"}],"trainingFinished",[{"createdDate":"2024-07-29T06:27:31Z","event":"trainingFinished","subtitle":"WeRest 1","title":"Training Completed","id":"E114BDB5-2293-4190-BB26-1ACF5C1D045D"}],"experimentCreated",[{"createdDate":"2024-07-29T06:15:05Z","event":"experimentCreated","id":"B65019D1-CAC1-4B88-889C-3E2BFDF74D03","title":"Model Source Created","subtitle":"WeRest 1"}],"trainingStarted",[{"event":"trainingStarted","title":"Training Started","createdDate":"2024-07-29T06:27:30Z","subtitle":"WeRest 1","id":"BB7643B8-663B-4041-8532-D9A682CA70AE"}]]}